<annotation verified="yes">
	<folder>董唯璇</folder>
	<filename>1068.jpeg</filename>
	<path>/home/shelly/桌面/董唯璇/1068.jpeg</path>
	<source>
		<database>Unknown</database>
	</source>
	<size>
		<width>1218</width>
		<height>1218</height>
		<depth>3</depth>
	</size>
	<segmented>0</segmented>
	<object>
		<name>Leconte</name>
		<pose>Unspecified</pose>
		<truncated>0</truncated>
		<difficult>0</difficult>
		<bndbox>
			<xmin>474</xmin>
			<ymin>503</ymin>
			<xmax>616</xmax>
			<ymax>564</ymax>
		</bndbox>
	</object>
	<object>
		<name>Leconte</name>
		<pose>Unspecified</pose>
		<truncated>0</truncated>
		<difficult>0</difficult>
		<bndbox>
			<xmin>445</xmin>
			<ymin>644</ymin>
			<xmax>571</xmax>
			<ymax>751</ymax>
		</bndbox>
	</object>
	<object>
		<name>Boerner</name>
		<pose>Unspecified</pose>
		<truncated>0</truncated>
		<difficult>0</difficult>
		<bndbox>
			<xmin>718</xmin>
			<ymin>547</ymin>
			<xmax>852</xmax>
			<ymax>633</ymax>
		</bndbox>
	</object>
	<object>
		<name>linnaeus</name>
		<pose>Unspecified</pose>
		<truncated>0</truncated>
		<difficult>0</difficult>
		<bndbox>
			<xmin>539</xmin>
			<ymin>814</ymin>
			<xmax>591</xmax>
			<ymax>898</ymax>
		</bndbox>
	</object>
	<object>
		<name>armandi</name>
		<pose>Unspecified</pose>
		<truncated>0</truncated>
		<difficult>0</difficult>
		<bndbox>
			<xmin>610</xmin>
			<ymin>758</ymin>
			<xmax>705</xmax>
			<ymax>794</ymax>
		</bndbox>
	</object>
	<object>
		<name>armandi</name>
		<pose>Unspecified</pose>
		<truncated>0</truncated>
		<difficult>0</difficult>
		<bndbox>
			<xmin>772</xmin>
			<ymin>717</ymin>
			<xmax>850</xmax>
			<ymax>779</ymax>
		</bndbox>
	</object>
	<object>
		<name>coleoptera</name>
		<pose>Unspecified</pose>
		<truncated>0</truncated>
		<difficult>0</difficult>
		<bndbox>
			<xmin>651</xmin>
			<ymin>456</ymin>
			<xmax>696</xmax>
			<ymax>503</ymax>
		</bndbox>
	</object>
</annotation>