<annotation>
	<folder>刘霏霏</folder>
	<filename>149.jpeg</filename>
	<path>/home/fion/桌面/刘霏霏/149.jpeg</path>
	<source>
		<database>Unknown</database>
	</source>
	<size>
		<width>1434</width>
		<height>1434</height>
		<depth>3</depth>
	</size>
	<segmented>0</segmented>
	<object>
		<name>Leconte</name>
		<pose>Unspecified</pose>
		<truncated>0</truncated>
		<difficult>0</difficult>
		<bndbox>
			<xmin>443</xmin>
			<ymin>422</ymin>
			<xmax>619</xmax>
			<ymax>542</ymax>
		</bndbox>
	</object>
	<object>
		<name>Boerner</name>
		<pose>Unspecified</pose>
		<truncated>0</truncated>
		<difficult>0</difficult>
		<bndbox>
			<xmin>746</xmin>
			<ymin>571</ymin>
			<xmax>895</xmax>
			<ymax>683</ymax>
		</bndbox>
	</object>
	<object>
		<name>coleoptera</name>
		<pose>Unspecified</pose>
		<truncated>0</truncated>
		<difficult>0</difficult>
		<bndbox>
			<xmin>602</xmin>
			<ymin>712</ymin>
			<xmax>687</xmax>
			<ymax>827</ymax>
		</bndbox>
	</object>
	<object>
		<name>linnaeus</name>
		<pose>Unspecified</pose>
		<truncated>0</truncated>
		<difficult>0</difficult>
		<bndbox>
			<xmin>697</xmin>
			<ymin>393</ymin>
			<xmax>778</xmax>
			<ymax>505</ymax>
		</bndbox>
	</object>
	<object>
		<name>armandi</name>
		<pose>Unspecified</pose>
		<truncated>0</truncated>
		<difficult>0</difficult>
		<bndbox>
			<xmin>417</xmin>
			<ymin>588</ymin>
			<xmax>524</xmax>
			<ymax>678</ymax>
		</bndbox>
	</object>
</annotation>