<annotation>
	<folder>张本润</folder>
	<filename>2039.jpeg</filename>
	<path>C:\Users\83885\Desktop\windows_v1.5.0\annotation\张本润\2039.jpeg</path>
	<source>
		<database>Unknown</database>
	</source>
	<size>
		<width>1250</width>
		<height>1250</height>
		<depth>3</depth>
	</size>
	<segmented>0</segmented>
	<object>
		<name>Leconte</name>
		<pose>Unspecified</pose>
		<truncated>0</truncated>
		<difficult>0</difficult>
		<bndbox>
			<xmin>478</xmin>
			<ymin>762</ymin>
			<xmax>614</xmax>
			<ymax>937</ymax>
		</bndbox>
	</object>
	<object>
		<name>Leconte</name>
		<pose>Unspecified</pose>
		<truncated>0</truncated>
		<difficult>0</difficult>
		<bndbox>
			<xmin>801</xmin>
			<ymin>457</ymin>
			<xmax>944</xmax>
			<ymax>559</ymax>
		</bndbox>
	</object>
	<object>
		<name>Boerner</name>
		<pose>Unspecified</pose>
		<truncated>0</truncated>
		<difficult>0</difficult>
		<bndbox>
			<xmin>734</xmin>
			<ymin>690</ymin>
			<xmax>818</xmax>
			<ymax>824</ymax>
		</bndbox>
	</object>
	<object>
		<name>acuminatus</name>
		<pose>Unspecified</pose>
		<truncated>0</truncated>
		<difficult>0</difficult>
		<bndbox>
			<xmin>800</xmin>
			<ymin>864</ymin>
			<xmax>875</xmax>
			<ymax>929</ymax>
		</bndbox>
	</object>
	<object>
		<name>Linnaeus</name>
		<pose>Unspecified</pose>
		<truncated>0</truncated>
		<difficult>0</difficult>
		<bndbox>
			<xmin>632</xmin>
			<ymin>780</ymin>
			<xmax>726</xmax>
			<ymax>836</ymax>
		</bndbox>
	</object>
	<object>
		<name>armandi</name>
		<pose>Unspecified</pose>
		<truncated>0</truncated>
		<difficult>0</difficult>
		<bndbox>
			<xmin>583</xmin>
			<ymin>632</ymin>
			<xmax>644</xmax>
			<ymax>723</ymax>
		</bndbox>
	</object>
	<object>
		<name>coleoptera</name>
		<pose>Unspecified</pose>
		<truncated>0</truncated>
		<difficult>0</difficult>
		<bndbox>
			<xmin>583</xmin>
			<ymin>516</ymin>
			<xmax>644</xmax>
			<ymax>564</ymax>
		</bndbox>
	</object>
</annotation>