<annotation>
	<folder>张本润</folder>
	<filename>2056.jpeg</filename>
	<path>C:\Users\83885\Desktop\windows_v1.5.0\annotation\张本润\2056.jpeg</path>
	<source>
		<database>Unknown</database>
	</source>
	<size>
		<width>1270</width>
		<height>1270</height>
		<depth>3</depth>
	</size>
	<segmented>0</segmented>
	<object>
		<name>acuminatus</name>
		<pose>Unspecified</pose>
		<truncated>0</truncated>
		<difficult>0</difficult>
		<bndbox>
			<xmin>477</xmin>
			<ymin>561</ymin>
			<xmax>554</xmax>
			<ymax>622</ymax>
		</bndbox>
	</object>
	<object>
		<name>Boerner</name>
		<pose>Unspecified</pose>
		<truncated>0</truncated>
		<difficult>0</difficult>
		<bndbox>
			<xmin>674</xmin>
			<ymin>547</ymin>
			<xmax>810</xmax>
			<ymax>655</ymax>
		</bndbox>
	</object>
	<object>
		<name>Leconte</name>
		<pose>Unspecified</pose>
		<truncated>0</truncated>
		<difficult>0</difficult>
		<bndbox>
			<xmin>622</xmin>
			<ymin>691</ymin>
			<xmax>733</xmax>
			<ymax>868</ymax>
		</bndbox>
	</object>
	<object>
		<name>armandi</name>
		<pose>Unspecified</pose>
		<truncated>0</truncated>
		<difficult>0</difficult>
		<bndbox>
			<xmin>822</xmin>
			<ymin>594</ymin>
			<xmax>907</xmax>
			<ymax>698</ymax>
		</bndbox>
	</object>
	<object>
		<name>coleoptera</name>
		<pose>Unspecified</pose>
		<truncated>0</truncated>
		<difficult>0</difficult>
		<bndbox>
			<xmin>750</xmin>
			<ymin>404</ymin>
			<xmax>802</xmax>
			<ymax>466</ymax>
		</bndbox>
	</object>
</annotation>