<annotation>
	<folder>张本润</folder>
	<filename>2067.jpeg</filename>
	<path>C:\Users\83885\Desktop\windows_v1.5.0\annotation\张本润\2067.jpeg</path>
	<source>
		<database>Unknown</database>
	</source>
	<size>
		<width>1228</width>
		<height>1228</height>
		<depth>3</depth>
	</size>
	<segmented>0</segmented>
	<object>
		<name>Leconte</name>
		<pose>Unspecified</pose>
		<truncated>0</truncated>
		<difficult>0</difficult>
		<bndbox>
			<xmin>650</xmin>
			<ymin>830</ymin>
			<xmax>784</xmax>
			<ymax>895</ymax>
		</bndbox>
	</object>
	<object>
		<name>Linnaeus</name>
		<pose>Unspecified</pose>
		<truncated>0</truncated>
		<difficult>0</difficult>
		<bndbox>
			<xmin>600</xmin>
			<ymin>698</ymin>
			<xmax>696</xmax>
			<ymax>754</ymax>
		</bndbox>
	</object>
	<object>
		<name>armandi</name>
		<pose>Unspecified</pose>
		<truncated>0</truncated>
		<difficult>0</difficult>
		<bndbox>
			<xmin>587</xmin>
			<ymin>479</ymin>
			<xmax>643</xmax>
			<ymax>558</ymax>
		</bndbox>
	</object>
	<object>
		<name>acuminatus</name>
		<pose>Unspecified</pose>
		<truncated>0</truncated>
		<difficult>0</difficult>
		<bndbox>
			<xmin>777</xmin>
			<ymin>505</ymin>
			<xmax>853</xmax>
			<ymax>553</ymax>
		</bndbox>
	</object>
	<object>
		<name>coleoptera</name>
		<pose>Unspecified</pose>
		<truncated>0</truncated>
		<difficult>0</difficult>
		<bndbox>
			<xmin>733</xmin>
			<ymin>621</ymin>
			<xmax>791</xmax>
			<ymax>664</ymax>
		</bndbox>
	</object>
	<object>
		<name>Boerner</name>
		<pose>Unspecified</pose>
		<truncated>0</truncated>
		<difficult>0</difficult>
		<bndbox>
			<xmin>828</xmin>
			<ymin>879</ymin>
			<xmax>964</xmax>
			<ymax>948</ymax>
		</bndbox>
	</object>
</annotation>