<annotation>
	<folder>张本润</folder>
	<filename>2218.jpeg</filename>
	<path>C:\Users\83885\Desktop\windows_v1.5.0\annotation\张本润\2218.jpeg</path>
	<source>
		<database>Unknown</database>
	</source>
	<size>
		<width>1232</width>
		<height>1232</height>
		<depth>3</depth>
	</size>
	<segmented>0</segmented>
	<object>
		<name>Leconte</name>
		<pose>Unspecified</pose>
		<truncated>0</truncated>
		<difficult>0</difficult>
		<bndbox>
			<xmin>650</xmin>
			<ymin>450</ymin>
			<xmax>776</xmax>
			<ymax>562</ymax>
		</bndbox>
	</object>
	<object>
		<name>Linnaeus</name>
		<pose>Unspecified</pose>
		<truncated>0</truncated>
		<difficult>0</difficult>
		<bndbox>
			<xmin>484</xmin>
			<ymin>677</ymin>
			<xmax>548</xmax>
			<ymax>772</ymax>
		</bndbox>
	</object>
	<object>
		<name>acuminatus</name>
		<pose>Unspecified</pose>
		<truncated>0</truncated>
		<difficult>0</difficult>
		<bndbox>
			<xmin>629</xmin>
			<ymin>583</ymin>
			<xmax>707</xmax>
			<ymax>639</ymax>
		</bndbox>
	</object>
	<object>
		<name>armandi</name>
		<pose>Unspecified</pose>
		<truncated>0</truncated>
		<difficult>0</difficult>
		<bndbox>
			<xmin>701</xmin>
			<ymin>641</ymin>
			<xmax>760</xmax>
			<ymax>732</ymax>
		</bndbox>
	</object>
	<object>
		<name>coleoptera</name>
		<pose>Unspecified</pose>
		<truncated>0</truncated>
		<difficult>0</difficult>
		<bndbox>
			<xmin>747</xmin>
			<ymin>764</ymin>
			<xmax>786</xmax>
			<ymax>827</ymax>
		</bndbox>
	</object>
</annotation>