<annotation>
	<folder>刘霏霏</folder>
	<filename>319.jpeg</filename>
	<path>/home/fion/桌面/刘霏霏/319.jpeg</path>
	<source>
		<database>Unknown</database>
	</source>
	<size>
		<width>1318</width>
		<height>1318</height>
		<depth>3</depth>
	</size>
	<segmented>0</segmented>
	<object>
		<name>Leconte</name>
		<pose>Unspecified</pose>
		<truncated>0</truncated>
		<difficult>0</difficult>
		<bndbox>
			<xmin>634</xmin>
			<ymin>797</ymin>
			<xmax>785</xmax>
			<ymax>923</ymax>
		</bndbox>
	</object>
	<object>
		<name>Boerner</name>
		<pose>Unspecified</pose>
		<truncated>0</truncated>
		<difficult>0</difficult>
		<bndbox>
			<xmin>578</xmin>
			<ymin>616</ymin>
			<xmax>719</xmax>
			<ymax>733</ymax>
		</bndbox>
	</object>
	<object>
		<name>linnaeus</name>
		<pose>Unspecified</pose>
		<truncated>0</truncated>
		<difficult>0</difficult>
		<bndbox>
			<xmin>531</xmin>
			<ymin>511</ymin>
			<xmax>629</xmax>
			<ymax>577</ymax>
		</bndbox>
	</object>
	<object>
		<name>armandi</name>
		<pose>Unspecified</pose>
		<truncated>0</truncated>
		<difficult>0</difficult>
		<bndbox>
			<xmin>784</xmin>
			<ymin>492</ymin>
			<xmax>853</xmax>
			<ymax>592</ymax>
		</bndbox>
	</object>
	<object>
		<name>coleoptera</name>
		<pose>Unspecified</pose>
		<truncated>0</truncated>
		<difficult>0</difficult>
		<bndbox>
			<xmin>809</xmin>
			<ymin>692</ymin>
			<xmax>892</xmax>
			<ymax>750</ymax>
		</bndbox>
	</object>
</annotation>