<annotation>
	<folder>刘霏霏</folder>
	<filename>321.jpeg</filename>
	<path>/home/fion/桌面/刘霏霏/321.jpeg</path>
	<source>
		<database>Unknown</database>
	</source>
	<size>
		<width>1296</width>
		<height>1296</height>
		<depth>3</depth>
	</size>
	<segmented>0</segmented>
	<object>
		<name>Leconte</name>
		<pose>Unspecified</pose>
		<truncated>0</truncated>
		<difficult>0</difficult>
		<bndbox>
			<xmin>530</xmin>
			<ymin>789</ymin>
			<xmax>693</xmax>
			<ymax>913</ymax>
		</bndbox>
	</object>
	<object>
		<name>Boerner</name>
		<pose>Unspecified</pose>
		<truncated>0</truncated>
		<difficult>0</difficult>
		<bndbox>
			<xmin>727</xmin>
			<ymin>482</ymin>
			<xmax>815</xmax>
			<ymax>647</ymax>
		</bndbox>
	</object>
	<object>
		<name>armandi</name>
		<pose>Unspecified</pose>
		<truncated>0</truncated>
		<difficult>0</difficult>
		<bndbox>
			<xmin>578</xmin>
			<ymin>408</ymin>
			<xmax>634</xmax>
			<ymax>516</ymax>
		</bndbox>
	</object>
	<object>
		<name>linnaeus</name>
		<pose>Unspecified</pose>
		<truncated>0</truncated>
		<difficult>0</difficult>
		<bndbox>
			<xmin>512</xmin>
			<ymin>650</ymin>
			<xmax>608</xmax>
			<ymax>718</ymax>
		</bndbox>
	</object>
	<object>
		<name>coleoptera</name>
		<pose>Unspecified</pose>
		<truncated>0</truncated>
		<difficult>0</difficult>
		<bndbox>
			<xmin>786</xmin>
			<ymin>718</ymin>
			<xmax>851</xmax>
			<ymax>794</ymax>
		</bndbox>
	</object>
</annotation>