<annotation>
	<folder>石霄宇</folder>
	<filename>547.jpeg</filename>
	<path>/home/sxy/已拍摄图片/石霄宇/石霄宇/石霄宇/547.jpeg</path>
	<source>
		<database>Unknown</database>
	</source>
	<size>
		<width>1218</width>
		<height>1218</height>
		<depth>3</depth>
	</size>
	<segmented>0</segmented>
	<object>
		<name>Boerner</name>
		<pose>Unspecified</pose>
		<truncated>0</truncated>
		<difficult>0</difficult>
		<bndbox>
			<xmin>450</xmin>
			<ymin>443</ymin>
			<xmax>582</xmax>
			<ymax>555</ymax>
		</bndbox>
	</object>
	<object>
		<name>Leconte</name>
		<pose>Unspecified</pose>
		<truncated>0</truncated>
		<difficult>0</difficult>
		<bndbox>
			<xmin>523</xmin>
			<ymin>613</ymin>
			<xmax>656</xmax>
			<ymax>711</ymax>
		</bndbox>
	</object>
	<object>
		<name>Linnaeus</name>
		<pose>Unspecified</pose>
		<truncated>0</truncated>
		<difficult>0</difficult>
		<bndbox>
			<xmin>639</xmin>
			<ymin>334</ymin>
			<xmax>733</xmax>
			<ymax>395</ymax>
		</bndbox>
	</object>
	<object>
		<name>coleoptera</name>
		<pose>Unspecified</pose>
		<truncated>0</truncated>
		<difficult>0</difficult>
		<bndbox>
			<xmin>769</xmin>
			<ymin>604</ymin>
			<xmax>842</xmax>
			<ymax>658</ymax>
		</bndbox>
	</object>
	<object>
		<name>armandi</name>
		<pose>Unspecified</pose>
		<truncated>0</truncated>
		<difficult>0</difficult>
		<bndbox>
			<xmin>784</xmin>
			<ymin>404</ymin>
			<xmax>841</xmax>
			<ymax>487</ymax>
		</bndbox>
	</object>
</annotation>